matisse_controller/__init__.py
matisse_controller/config/__init__.py
matisse_controller/config/configuration.py
matisse_controller/config/names.py
matisse_controller/config/tooltips.py
matisse_controller/gui/__init__.py
matisse_controller/gui/control_application.py
matisse_controller/gui/logging_stream.py
matisse_controller/gui/utils.py
matisse_controller/gui/dialogs/__init__.py
matisse_controller/gui/dialogs/configuration_dialog.py
matisse_controller/gui/dialogs/ple_analysis_dialog.py
matisse_controller/gui/dialogs/ple_scan_dialog.py
matisse_controller/gui/dialogs/single_acquisition_dialog.py
matisse_controller/gui/threads/__init__.py
matisse_controller/gui/threads/exit_flag.py
matisse_controller/gui/threads/logging_thread.py
matisse_controller/gui/threads/status_update_thread.py
matisse_controller/gui/widgets/__init__.py
matisse_controller/gui/widgets/logging_area.py
matisse_controller/gui/widgets/status_monitor.py
matisse_controller/matisse/__init__.py
matisse_controller/matisse/constants.py
matisse_controller/matisse/control_loops_on.py
matisse_controller/matisse/event_report.py
matisse_controller/matisse/lock_correction_thread.py
matisse_controller/matisse/matisse.py
matisse_controller/matisse/sample_scans.py
matisse_controller/matisse/stabilization_thread.py
matisse_controller/matisse/plotting/__init__.py
matisse_controller/matisse/plotting/birefringent_filter_scan_plot_process.py
matisse_controller/matisse/plotting/thin_etalon_scan_plot_process.py
matisse_controller/shamrock_ple/__init__.py
matisse_controller/shamrock_ple/ccd.py
matisse_controller/shamrock_ple/constants.py
matisse_controller/shamrock_ple/ple.py
matisse_controller/shamrock_ple/shamrock.py
matisse_controller/shamrock_ple/utils.py
matisse_controller/shamrock_ple/lib/README.md
matisse_controller/shamrock_ple/plotting/__init__.py
matisse_controller/shamrock_ple/plotting/ple_analysis_plot_process.py
matisse_controller/shamrock_ple/plotting/spectrum_plot_process.py
matisse_controller-0.4.0.dist-info/LICENSE
matisse_controller-0.4.0.dist-info/METADATA
matisse_controller-0.4.0.dist-info/WHEEL
matisse_controller-0.4.0.dist-info/entry_points.txt
matisse_controller-0.4.0.dist-info/top_level.txt
matisse_controller-0.4.0.dist-info/RECORD
