Metadata-Version: 2.1
Name: matisse-controller
Version: 0.4.0
Summary: A Python package to control the Matisse 2 TS.
Home-page: https://lucis-fluxum.github.io/matisse-controller/
Author: Luc Street
License: MIT
Project-URL: Documentation, https://lucis-fluxum.github.io/matisse-controller/docs/
Project-URL: Source Code, https://github.com/lucis-fluxum/matisse-controller
Keywords: ni-visa matisse laser
Platform: UNKNOWN
Classifier: Development Status :: 4 - Beta
Classifier: Intended Audience :: Developers
Classifier: Intended Audience :: Science/Research
Classifier: License :: OSI Approved :: MIT License
Classifier: Programming Language :: Python :: 3 :: Only
Classifier: Programming Language :: Python :: 3.7
Classifier: Topic :: Scientific/Engineering :: Physics
Requires-Python: ~=3.7
Requires-Dist: pyvisa (<2,>=1)
Requires-Dist: pyserial (<4,>=3)
Requires-Dist: scipy (<2,>=1)
Requires-Dist: matplotlib (<4,>=3)
Requires-Dist: pyqt5 (>=5)
Requires-Dist: bidict (>=0.18)
Requires-Dist: glom (>=19.2)
